pvcast/__init__.py
pvcast/__main__.py
pvcast/commandline/__init__.py
pvcast/commandline/commandline.py
pvcast/config/__init__.py
pvcast/config/configreader.py
pvcast/const.py
pvcast/data/proc/cec_inverters.csv
pvcast/data/proc/cec_modules.csv
pvcast/homeassistant/__init__.py
pvcast/homeassistant/homeassistantapi.py
pvcast/model/__init__.py
pvcast/model/const.py
pvcast/model/forecasting.py
pvcast/model/model.py
pvcast/util/__init__.py
pvcast/util/timestamps.py
pvcast/util/units.py
pvcast/weather/__init__.py
pvcast/weather/clearoutside.py
pvcast/weather/homeassistant.py
pvcast/weather/weather.py
pvcast/webserver/__init__.py
pvcast/webserver/app.py
pvcast/webserver/const.py
pvcast/webserver/models/__init__.py
pvcast/webserver/models/base.py
pvcast/webserver/models/clearsky.py
pvcast/webserver/models/historical.py
pvcast/webserver/models/live.py
pvcast/webserver/routers/__init__.py
pvcast/webserver/routers/clearsky.py
pvcast/webserver/routers/dependencies.py
pvcast/webserver/routers/helpers.py
pvcast/webserver/routers/historical.py
pvcast/webserver/routers/live.py
pvcast/webserver/routers/utils.py
pvcast/webserver/static/favicon.png
pvcast-0.2.0.dist-info/METADATA
pvcast-0.2.0.dist-info/WHEEL
pvcast-0.2.0.dist-info/RECORD
